MANIFEST.in
README.md
setup.py
django_remplacer.egg-info/PKG-INFO
django_remplacer.egg-info/SOURCES.txt
django_remplacer.egg-info/dependency_links.txt
django_remplacer.egg-info/not-zip-safe
django_remplacer.egg-info/top_level.txt
remplacer/__init__.py
remplacer/models.py
remplacer/settings.py
remplacer/management/__init__.py
remplacer/management/commands/__init__.py
remplacer/management/commands/remplace.py